golm/__init__.py
golm/console.py
golm/db.sqlite3
golm/manage.py
golm/core/__init__.py
golm/core/chat_session.py
golm/core/context.py
golm/core/dialog_manager.py
golm/core/flow.py
golm/core/logger.py
golm/core/message_logger.py
golm/core/message_parser.py
golm/core/persistence.py
golm/core/serialize.py
golm/core/tasks.py
golm/core/templates.py
golm/core/tests.py
golm/core/__pycache__/__init__.cpython-36.pyc
golm/core/__pycache__/chat_session.cpython-36.pyc
golm/core/__pycache__/message_logger.cpython-36.pyc
golm/core/__pycache__/message_parser.cpython-36.pyc
golm/core/__pycache__/persistence.cpython-36.pyc
golm/core/__pycache__/serialize.cpython-36.pyc
golm/core/__pycache__/tasks.cpython-36.pyc
golm/core/__pycache__/tests.cpython-36.pyc
golm/core/interfaces/__init__.py
golm/core/interfaces/all.py
golm/core/interfaces/facebook.py
golm/core/interfaces/microsoft.py
golm/core/interfaces/telegram.py
golm/core/interfaces/test.py
golm/core/interfaces/__pycache__/__init__.cpython-36.pyc
golm/core/interfaces/__pycache__/all.cpython-36.pyc
golm/core/interfaces/__pycache__/facebook.cpython-36.pyc
golm/core/interfaces/__pycache__/microsoft.cpython-36.pyc
golm/core/interfaces/__pycache__/telegram.cpython-36.pyc
golm/core/interfaces/__pycache__/test.cpython-36.pyc
golm/core/interfaces/adapter/microsoft.py
golm/core/interfaces/adapter/telegram.py
golm/core/interfaces/adapter/__pycache__/microsoft.cpython-36.pyc
golm/core/nlp/__init__.py
golm/core/nlp/classify.py
golm/core/nlp/cleanup.py
golm/core/nlp/data_model.py
golm/core/nlp/duckling.py
golm/core/nlp/geneea.py
golm/core/nlp/glove.py
golm/core/nlp/keywords.py
golm/core/nlp/train.py
golm/core/nlp/utils.py
golm/core/nlp/__pycache__/__init__.cpython-36.pyc
golm/core/nlp/__pycache__/cleanup.cpython-36.pyc
golm/core/nlp/__pycache__/data_model.cpython-36.pyc
golm/core/nlp/__pycache__/utils.cpython-36.pyc
golm/core/nlp/gui/__init__.py
golm/core/nlp/gui/forms.py
golm-0.9.1b0.dist-info/DESCRIPTION.rst
golm-0.9.1b0.dist-info/METADATA
golm-0.9.1b0.dist-info/RECORD
golm-0.9.1b0.dist-info/WHEEL
golm-0.9.1b0.dist-info/entry_points.txt
golm-0.9.1b0.dist-info/metadata.json
golm-0.9.1b0.dist-info/top_level.txt
