Metadata-Version: 2.0
Name: golm
Version: 0.9.1b0
Summary: Framework for creating chatbots for Messenger and other platforms.
Home-page: https://github.com/prihoda/golm
Author: David Příhoda, Jakub Drdák, Matúš Žilinec
Author-email: david.prihoda@gmail.com
License: Apache Software License
Platform: UNKNOWN
Classifier: Environment :: Web Environment
Classifier: Framework :: Django
Classifier: Intended Audience :: Developers
Classifier: License :: OSI Approved :: Apache Software License
Classifier: Operating System :: OS Independent
Classifier: Programming Language :: Python
Classifier: Programming Language :: Python :: 3
Classifier: Programming Language :: Python :: 3.4
Classifier: Programming Language :: Python :: 3.5
Classifier: Programming Language :: Python :: 3.6
Classifier: Topic :: Internet :: WWW/HTTP
Classifier: Topic :: Internet :: WWW/HTTP :: Dynamic Content
Requires-Dist: celery (==4.0.2)
Requires-Dist: django (==2.0.3)
Requires-Dist: emoji
Requires-Dist: python-dateutil
Requires-Dist: pytz
Requires-Dist: redis
Requires-Dist: requests
Requires-Dist: unidecode
Requires-Dist: wheel
Requires-Dist: wit
